{"topTotalScore":666,"lowTotalScore":432,"topScoreYesterday":9,"lowScoreYesterday":0,"leaders":[{"pos":1,"teamName":"les Ducks","goals":240,"passes":362,"goaliesWins":44,"goaliesShutOuts":10,"points":666,"goalsDiff":4,"passesDiff":1,"goaliesWinDiff":0,"goaliesShutOutsDiff":0,"pointsDiff":5,"userLogo":"michel.png","bigLogo":"michel.png","smallLogo":"michel.png","teamUserName":"Michel","playForCash":false,"hasPaid":false,"diffPosition":0},{"pos":2,"teamName":"Faucon pèlerin","goals":222,"passes":339,"goaliesWins":38,"goaliesShutOuts":7,"points":613,"goalsDiff":5,"passesDiff":4,"goaliesWinDiff":0,"goaliesShutOutsDiff":0,"pointsDiff":9,"userLogo":"andre.png","bigLogo":"andre.png","smallLogo":"andre.png","teamUserName":"Andre","playForCash":false,"hasPaid":false,"diffPosition":0},{"pos":3,"teamName":"Laser Kiwis","goals":231,"passes":321,"goaliesWins":33,"goaliesShutOuts":7,"points":599,"goalsDiff":3,"passesDiff":0,"goaliesWinDiff":0,"goaliesShutOutsDiff":0,"pointsDiff":3,"userLogo":"guillaume.png","bigLogo":"guillaume.png","smallLogo":"guillaume.png","teamUserName":"Guillaume","playForCash":false,"hasPaid":false,"diffPosition":0},{"pos":4,"teamName":"La SkiBum","goals":213,"passes":336,"goaliesWins":36,"goaliesShutOuts":2,"points":589,"goalsDiff":1,"passesDiff":2,"goaliesWinDiff":0,"goaliesShutOutsDiff":0,"pointsDiff":3,"userLogo":"jolyne.png","bigLogo":"jolyne.png","smallLogo":"jolyne.png","teamUserName":"Jolyne","playForCash":false,"hasPaid":false,"diffPosition":0},{"pos":5,"teamName":"Les huards","goals":206,"passes":309,"goaliesWins":46,"goaliesShutOuts":8,"points":577,"goalsDiff":3,"passesDiff":0,"goaliesWinDiff":0,"goaliesShutOutsDiff":0,"pointsDiff":3,"userLogo":"louise.png","bigLogo":"louise.png","smallLogo":"louise.png","teamUserName":"Louise","playForCash":false,"hasPaid":false,"diffPosition":0},{"pos":6,"teamName":"Les Bizzares","goals":202,"passes":321,"goaliesWins":33,"goaliesShutOuts":7,"points":570,"goalsDiff":0,"passesDiff":0,"goaliesWinDiff":0,"goaliesShutOutsDiff":0,"pointsDiff":0,"userLogo":"jackson.png","bigLogo":"jackson.png","smallLogo":"jackson.png","teamUserName":"Jackson","playForCash":false,"hasPaid":false,"diffPosition":0},{"pos":7,"teamName":"Tiger","goals":197,"passes":306,"goaliesWins":47,"goaliesShutOuts":5,"points":560,"goalsDiff":0,"passesDiff":1,"goaliesWinDiff":0,"goaliesShutOutsDiff":0,"pointsDiff":1,"userLogo":"gaby.png","bigLogo":"gaby.png","smallLogo":"gaby.png","teamUserName":"Gabriel Pellerin","playForCash":false,"hasPaid":false,"diffPosition":0},{"pos":8,"teamName":"Équipe hommage à Dale Weise","goals":192,"passes":331,"goaliesWins":26,"goaliesShutOuts":3,"points":555,"goalsDiff":0,"passesDiff":0,"goaliesWinDiff":0,"goaliesShutOutsDiff":0,"pointsDiff":0,"userLogo":"alexandre.png","bigLogo":"alexandre.png","smallLogo":"alexandre.png","teamUserName":"Alexandre","playForCash":false,"hasPaid":false,"diffPosition":0},{"pos":9,"teamName":"Les Loupouise","goals":171,"passes":334,"goaliesWins":28,"goaliesShutOuts":3,"points":539,"goalsDiff":2,"passesDiff":1,"goaliesWinDiff":0,"goaliesShutOutsDiff":0,"pointsDiff":3,"userLogo":"louise_p.png","bigLogo":"louise_p.png","smallLogo":"louise_p.png","teamUserName":"Louise_p","playForCash":false,"hasPaid":false,"diffPosition":0},{"pos":10,"teamName":"Hell Roll","goals":199,"passes":298,"goaliesWins":31,"goaliesShutOuts":3,"points":534,"goalsDiff":2,"passesDiff":0,"goaliesWinDiff":0,"goaliesShutOutsDiff":0,"pointsDiff":2,"userLogo":"vincent.png","bigLogo":"vincent.png","smallLogo":"vincent.png","teamUserName":"Vincent","playForCash":false,"hasPaid":false,"diffPosition":0},{"pos":11,"teamName":"Bamboozlers","goals":195,"passes":289,"goaliesWins":31,"goaliesShutOuts":3,"points":521,"goalsDiff":3,"passesDiff":2,"goaliesWinDiff":0,"goaliesShutOutsDiff":0,"pointsDiff":5,"userLogo":"hugo.png","bigLogo":"hugo.png","smallLogo":"hugo.png","teamUserName":"Hugo","playForCash":false,"hasPaid":false,"diffPosition":1},{"pos":12,"teamName":"dog person","goals":198,"passes":276,"goaliesWins":35,"goaliesShutOuts":5,"points":519,"goalsDiff":0,"passesDiff":0,"goaliesWinDiff":0,"goaliesShutOutsDiff":0,"pointsDiff":0,"userLogo":"eve.png","bigLogo":"eve.png","smallLogo":"eve.png","teamUserName":"Eve","playForCash":false,"hasPaid":false,"diffPosition":-1},{"pos":13,"teamName":"Lougaroc","goals":159,"passes":307,"goaliesWins":44,"goaliesShutOuts":4,"points":518,"goalsDiff":2,"passesDiff":1,"goaliesWinDiff":0,"goaliesShutOutsDiff":0,"pointsDiff":3,"userLogo":"maddox.png","bigLogo":"maddox.png","smallLogo":"maddox.png","teamUserName":"Maddox","playForCash":false,"hasPaid":false,"diffPosition":0},{"pos":14,"teamName":"Dwayne Johnson","goals":161,"passes":285,"goaliesWins":37,"goaliesShutOuts":4,"points":491,"goalsDiff":1,"passesDiff":0,"goaliesWinDiff":1,"goaliesShutOutsDiff":0,"pointsDiff":2,"userLogo":"elrick.png","bigLogo":"elrick.png","smallLogo":"elrick.png","teamUserName":"Elrick","playForCash":false,"hasPaid":false,"diffPosition":0},{"pos":15,"teamName":"Les Go et Lent","goals":160,"passes":242,"goaliesWins":28,"goaliesShutOuts":1,"points":432,"goalsDiff":0,"passesDiff":0,"goaliesWinDiff":0,"goaliesShutOutsDiff":0,"pointsDiff":0,"userLogo":"guy.png","bigLogo":"guy.png","smallLogo":"guy.png","teamUserName":"Guy","playForCash":false,"hasPaid":false,"diffPosition":0}],"bestLast7Days":{"pos":0,"teamName":"les Ducks","goals":240,"passes":362,"goaliesWins":44,"goaliesShutOuts":10,"points":666,"goalsDiff":17,"passesDiff":17,"goaliesWinDiff":2,"goaliesShutOutsDiff":0,"pointsDiff":36,"userLogo":"michel.png","bigLogo":"michel.png","smallLogo":"michel.png","teamUserName":"Michel","playForCash":false,"hasPaid":false,"diffPosition":0},"bestLast28Days":{"pos":0,"teamName":"les Ducks","goals":240,"passes":362,"goaliesWins":44,"goaliesShutOuts":10,"points":666,"goalsDiff":49,"passesDiff":88,"goaliesWinDiff":9,"goaliesShutOutsDiff":0,"pointsDiff":146,"userLogo":"michel.png","bigLogo":"michel.png","smallLogo":"michel.png","teamUserName":"Michel","playForCash":false,"hasPaid":false,"diffPosition":0},"bestLast14Days":{"pos":0,"teamName":"Faucon pèlerin","goals":222,"passes":339,"goaliesWins":38,"goaliesShutOuts":7,"points":613,"goalsDiff":37,"passesDiff":53,"goaliesWinDiff":5,"goaliesShutOutsDiff":0,"pointsDiff":95,"userLogo":"andre.png","bigLogo":"andre.png","smallLogo":"andre.png","teamUserName":"Andre","playForCash":false,"hasPaid":false,"diffPosition":0},"bestYesterday":{"pos":0,"teamName":"Faucon pèlerin","goals":222,"passes":339,"goaliesWins":38,"goaliesShutOuts":7,"points":613,"goalsDiff":5,"passesDiff":4,"goaliesWinDiff":0,"goaliesShutOutsDiff":0,"pointsDiff":9,"userLogo":"andre.png","bigLogo":"andre.png","smallLogo":"andre.png","teamUserName":"Andre","playForCash":false,"hasPaid":false,"diffPosition":0},"bestTonight":{"pos":0,"goals":0,"passes":0,"goaliesWins":0,"goaliesShutOuts":0,"points":0,"goalsDiff":0,"passesDiff":0,"goaliesWinDiff":0,"goaliesShutOutsDiff":0,"pointsDiff":0,"playForCash":false,"hasPaid":false,"diffPosition":0},"worstLast7Days":{"pos":0,"teamName":"Tiger","goals":197,"passes":306,"goaliesWins":47,"goaliesShutOuts":5,"points":560,"goalsDiff":6,"passesDiff":5,"goaliesWinDiff":2,"goaliesShutOutsDiff":0,"pointsDiff":13,"userLogo":"gaby.png","bigLogo":"gaby.png","smallLogo":"gaby.png","teamUserName":"Gabriel Pellerin","playForCash":false,"hasPaid":false,"diffPosition":0},"worstLast28Days":{"pos":0,"teamName":"Les Go et Lent","goals":160,"passes":242,"goaliesWins":28,"goaliesShutOuts":1,"points":432,"goalsDiff":37,"passesDiff":48,"goaliesWinDiff":10,"goaliesShutOutsDiff":0,"pointsDiff":95,"userLogo":"guy.png","bigLogo":"guy.png","smallLogo":"guy.png","teamUserName":"Guy","playForCash":false,"hasPaid":false,"diffPosition":0},"worstLast14Days":{"pos":0,"teamName":"Les Go et Lent","goals":160,"passes":242,"goaliesWins":28,"goaliesShutOuts":1,"points":432,"goalsDiff":14,"passesDiff":17,"goaliesWinDiff":6,"goaliesShutOutsDiff":0,"pointsDiff":37,"userLogo":"guy.png","bigLogo":"guy.png","smallLogo":"guy.png","teamUserName":"Guy","playForCash":false,"hasPaid":false,"diffPosition":0},"worstYesterday":{"pos":0,"teamName":"dog person","goals":198,"passes":276,"goaliesWins":35,"goaliesShutOuts":5,"points":519,"goalsDiff":0,"passesDiff":0,"goaliesWinDiff":0,"goaliesShutOutsDiff":0,"pointsDiff":0,"userLogo":"eve.png","bigLogo":"eve.png","smallLogo":"eve.png","teamUserName":"Eve","playForCash":false,"hasPaid":false,"diffPosition":0}}