{"topTotalScore":961,"lowTotalScore":700,"topScoreYesterday":9,"lowScoreYesterday":1,"leaders":[{"pos":1,"teamName":"Sorel-Tracy Hockey Club","goals":351,"passes":535,"goaliesWins":63,"goaliesShutOuts":6,"points":961,"goalsDiff":1,"passesDiff":3,"goaliesWinDiff":0,"goaliesShutOutsDiff":0,"pointsDiff":4,"userLogo":"alexandre.png","bigLogo":"alexandre.png","smallLogo":"alexandre.png","teamUserName":"Alexandre","playForCash":true,"hasPaid":false,"diffPosition":0},{"pos":2,"teamName":"Les Remparts","goals":340,"passes":496,"goaliesWins":60,"goaliesShutOuts":3,"points":902,"goalsDiff":1,"passesDiff":2,"goaliesWinDiff":0,"goaliesShutOutsDiff":0,"pointsDiff":3,"userLogo":"jean-pierre.png","bigLogo":"jean-pierre.png","smallLogo":"jean-pierre.png","teamUserName":"Jean-Pierre","playForCash":true,"hasPaid":false,"diffPosition":0},{"pos":3,"teamName":"Moose Hunter","goals":320,"passes":494,"goaliesWins":67,"goaliesShutOuts":5,"points":891,"goalsDiff":2,"passesDiff":2,"goaliesWinDiff":0,"goaliesShutOutsDiff":0,"pointsDiff":4,"userLogo":"vincent.png","bigLogo":"vincent.png","smallLogo":"vincent.png","teamUserName":"Vincent","playForCash":true,"hasPaid":false,"diffPosition":0},{"pos":4,"teamName":"Dream team","goals":336,"passes":481,"goaliesWins":46,"goaliesShutOuts":5,"points":873,"goalsDiff":3,"passesDiff":6,"goaliesWinDiff":0,"goaliesShutOutsDiff":0,"pointsDiff":9,"userLogo":"jean-daniel.png","bigLogo":"jean-daniel.png","smallLogo":"jean-daniel.png","teamUserName":"Jean-Daniel","playForCash":true,"hasPaid":true,"diffPosition":1},{"pos":5,"teamName":"Laser Kiwi","goals":295,"passes":526,"goaliesWins":45,"goaliesShutOuts":2,"points":870,"goalsDiff":2,"passesDiff":2,"goaliesWinDiff":0,"goaliesShutOutsDiff":0,"pointsDiff":4,"userLogo":"guillaume.png","bigLogo":"guillaume.png","smallLogo":"guillaume.png","teamUserName":"Guillaume","playForCash":true,"hasPaid":true,"diffPosition":-1},{"pos":6,"teamName":"Les Louplouises","goals":317,"passes":488,"goaliesWins":57,"goaliesShutOuts":3,"points":868,"goalsDiff":1,"passesDiff":3,"goaliesWinDiff":0,"goaliesShutOutsDiff":0,"pointsDiff":4,"userLogo":"louise_p.png","bigLogo":"louise_p.png","smallLogo":"louise_p.png","teamUserName":"Louise_p","playForCash":true,"hasPaid":true,"diffPosition":-1},{"pos":7,"teamName":"Les Go et Lent","goals":315,"passes":475,"goaliesWins":67,"goaliesShutOuts":5,"points":867,"goalsDiff":3,"passesDiff":3,"goaliesWinDiff":0,"goaliesShutOutsDiff":0,"pointsDiff":6,"userLogo":"guy.png","bigLogo":"guy.png","smallLogo":"guy.png","teamUserName":"Guy","playForCash":true,"hasPaid":true,"diffPosition":-1},{"pos":8,"teamName":"Maman Girafe","goals":279,"passes":516,"goaliesWins":48,"goaliesShutOuts":4,"points":851,"goalsDiff":1,"passesDiff":4,"goaliesWinDiff":0,"goaliesShutOutsDiff":0,"pointsDiff":5,"userLogo":"sylvianne.png","bigLogo":"sylvianne.png","smallLogo":"sylvianne.png","teamUserName":"Sylvianne","playForCash":false,"hasPaid":false,"diffPosition":-1},{"pos":9,"teamName":"Ski Bum","goals":291,"passes":486,"goaliesWins":59,"goaliesShutOuts":6,"points":848,"goalsDiff":3,"passesDiff":4,"goaliesWinDiff":0,"goaliesShutOutsDiff":0,"pointsDiff":7,"userLogo":"jolyne.png","bigLogo":"jolyne.png","smallLogo":"jolyne.png","teamUserName":"Jolyne","playForCash":true,"hasPaid":true,"diffPosition":0},{"pos":10,"teamName":"Les Ducks","goals":300,"passes":487,"goaliesWins":55,"goaliesShutOuts":2,"points":846,"goalsDiff":0,"passesDiff":2,"goaliesWinDiff":0,"goaliesShutOutsDiff":0,"pointsDiff":2,"userLogo":"michel.png","bigLogo":"michel.png","smallLogo":"michel.png","teamUserName":"Michel","playForCash":true,"hasPaid":true,"diffPosition":-2},{"pos":11,"teamName":"La Goth d\u0027Ottawa","goals":310,"passes":478,"goaliesWins":47,"goaliesShutOuts":2,"points":839,"goalsDiff":0,"passesDiff":1,"goaliesWinDiff":0,"goaliesShutOutsDiff":0,"pointsDiff":1,"userLogo":"eve.png","bigLogo":"eve.png","smallLogo":"eve.png","teamUserName":"Eve","playForCash":true,"hasPaid":true,"diffPosition":-1},{"pos":12,"teamName":"Chou Canadiens Chou","goals":312,"passes":447,"goaliesWins":59,"goaliesShutOuts":6,"points":830,"goalsDiff":2,"passesDiff":6,"goaliesWinDiff":0,"goaliesShutOutsDiff":0,"pointsDiff":8,"userLogo":"simon.png","bigLogo":"simon.png","smallLogo":"simon.png","teamUserName":"Simon","playForCash":false,"hasPaid":false,"diffPosition":0},{"pos":13,"teamName":"Les huards","goals":292,"passes":485,"goaliesWins":47,"goaliesShutOuts":2,"points":828,"goalsDiff":2,"passesDiff":2,"goaliesWinDiff":0,"goaliesShutOutsDiff":0,"pointsDiff":4,"userLogo":"louise.png","bigLogo":"louise.png","smallLogo":"louise.png","teamUserName":"Louise","playForCash":true,"hasPaid":true,"diffPosition":-2},{"pos":14,"teamName":"Les Immunologistes","goals":316,"passes":448,"goaliesWins":49,"goaliesShutOuts":3,"points":819,"goalsDiff":2,"passesDiff":2,"goaliesWinDiff":0,"goaliesShutOutsDiff":0,"pointsDiff":4,"userLogo":"vicky.png","bigLogo":"vicky.png","smallLogo":"vicky.png","teamUserName":"Vicky","playForCash":true,"hasPaid":true,"diffPosition":-1},{"pos":15,"teamName":"Les Bizzares","goals":255,"passes":498,"goaliesWins":58,"goaliesShutOuts":2,"points":815,"goalsDiff":2,"passesDiff":2,"goaliesWinDiff":0,"goaliesShutOutsDiff":0,"pointsDiff":4,"userLogo":"jackson.png","bigLogo":"jackson.png","smallLogo":"jackson.png","teamUserName":"Jackson","playForCash":true,"hasPaid":true,"diffPosition":-1},{"pos":16,"teamName":"L’Ydre de l’èrne","goals":280,"passes":464,"goaliesWins":54,"goaliesShutOuts":6,"points":810,"goalsDiff":0,"passesDiff":4,"goaliesWinDiff":0,"goaliesShutOutsDiff":0,"pointsDiff":4,"userLogo":"maddox.png","bigLogo":"maddox.png","smallLogo":"maddox.png","teamUserName":"Maddox","playForCash":true,"hasPaid":true,"diffPosition":-1},{"pos":17,"teamName":"WoW","goals":266,"passes":458,"goaliesWins":62,"goaliesShutOuts":3,"points":792,"goalsDiff":2,"passesDiff":5,"goaliesWinDiff":0,"goaliesShutOutsDiff":0,"pointsDiff":7,"userLogo":"hugo.png","bigLogo":"hugo.png","smallLogo":"hugo.png","teamUserName":"Hugo","playForCash":true,"hasPaid":true,"diffPosition":-1},{"pos":18,"teamName":"Les Flo Yo!","goals":300,"passes":453,"goaliesWins":34,"goaliesShutOuts":2,"points":791,"goalsDiff":1,"passesDiff":5,"goaliesWinDiff":0,"goaliesShutOutsDiff":0,"pointsDiff":6,"userLogo":"florence.png","bigLogo":"florence.png","smallLogo":"florence.png","teamUserName":"Florence","playForCash":false,"hasPaid":false,"diffPosition":-2},{"pos":19,"teamName":"The Chihuahuas","goals":307,"passes":404,"goaliesWins":61,"goaliesShutOuts":5,"points":782,"goalsDiff":3,"passesDiff":2,"goaliesWinDiff":0,"goaliesShutOutsDiff":0,"pointsDiff":5,"userLogo":"julien.png","bigLogo":"julien.png","smallLogo":"julien.png","teamUserName":"Julien","playForCash":false,"hasPaid":false,"diffPosition":-2},{"pos":20,"teamName":"Faucon","goals":262,"passes":460,"goaliesWins":46,"goaliesShutOuts":2,"points":772,"goalsDiff":3,"passesDiff":3,"goaliesWinDiff":0,"goaliesShutOutsDiff":0,"pointsDiff":6,"userLogo":"andre.png","bigLogo":"andre.png","smallLogo":"andre.png","teamUserName":"Andre","playForCash":true,"hasPaid":true,"diffPosition":-2},{"pos":21,"teamName":"The Angry Polar Bears","goals":244,"passes":448,"goaliesWins":47,"goaliesShutOuts":2,"points":743,"goalsDiff":0,"passesDiff":3,"goaliesWinDiff":0,"goaliesShutOutsDiff":0,"pointsDiff":3,"userLogo":"etienne.png","bigLogo":"etienne.png","smallLogo":"etienne.png","teamUserName":"Etienne","playForCash":false,"hasPaid":false,"diffPosition":-2},{"pos":22,"teamName":"Kyle Crane","goals":212,"passes":429,"goaliesWins":55,"goaliesShutOuts":2,"points":700,"goalsDiff":1,"passesDiff":5,"goaliesWinDiff":0,"goaliesShutOutsDiff":0,"pointsDiff":6,"userLogo":"elrick.png","bigLogo":"elrick.png","smallLogo":"elrick.png","teamUserName":"Elrick","playForCash":true,"hasPaid":true,"diffPosition":-2}],"bestLast7Days":{"pos":0,"teamName":"Ski Bum","goals":291,"passes":486,"goaliesWins":59,"goaliesShutOuts":6,"points":848,"goalsDiff":5,"passesDiff":8,"goaliesWinDiff":1,"goaliesShutOutsDiff":0,"pointsDiff":14,"userLogo":"jolyne.png","bigLogo":"jolyne.png","smallLogo":"jolyne.png","teamUserName":"Jolyne","playForCash":false,"hasPaid":false,"diffPosition":0},"bestLast28Days":{"pos":0,"teamName":"Sorel-Tracy Hockey Club","goals":351,"passes":535,"goaliesWins":63,"goaliesShutOuts":6,"points":961,"goalsDiff":67,"passesDiff":103,"goaliesWinDiff":11,"goaliesShutOutsDiff":2,"pointsDiff":185,"userLogo":"alexandre.png","bigLogo":"alexandre.png","smallLogo":"alexandre.png","teamUserName":"Alexandre","playForCash":false,"hasPaid":false,"diffPosition":0},"bestLast14Days":{"pos":0,"teamName":"Les Go et Lent","goals":315,"passes":475,"goaliesWins":67,"goaliesShutOuts":5,"points":867,"goalsDiff":23,"passesDiff":35,"goaliesWinDiff":4,"goaliesShutOutsDiff":0,"pointsDiff":62,"userLogo":"guy.png","bigLogo":"guy.png","smallLogo":"guy.png","teamUserName":"Guy","playForCash":false,"hasPaid":false,"diffPosition":0},"bestYesterday":{"pos":0,"teamName":"Dream team","goals":336,"passes":481,"goaliesWins":46,"goaliesShutOuts":5,"points":873,"goalsDiff":3,"passesDiff":6,"goaliesWinDiff":0,"goaliesShutOutsDiff":0,"pointsDiff":9,"userLogo":"jean-daniel.png","bigLogo":"jean-daniel.png","smallLogo":"jean-daniel.png","teamUserName":"Jean-Daniel","playForCash":false,"hasPaid":false,"diffPosition":0},"bestTonight":{"pos":0,"goals":0,"passes":0,"goaliesWins":0,"goaliesShutOuts":0,"points":0,"goalsDiff":0,"passesDiff":0,"goaliesWinDiff":0,"goaliesShutOutsDiff":0,"pointsDiff":0,"playForCash":false,"hasPaid":false,"diffPosition":0},"worstLast7Days":{"pos":0,"teamName":"La Goth d\u0027Ottawa","goals":310,"passes":478,"goaliesWins":47,"goaliesShutOuts":2,"points":839,"goalsDiff":-55,"passesDiff":-56,"goaliesWinDiff":0,"goaliesShutOutsDiff":0,"pointsDiff":-111,"userLogo":"eve.png","bigLogo":"eve.png","smallLogo":"eve.png","teamUserName":"Eve","playForCash":false,"hasPaid":false,"diffPosition":0},"worstLast28Days":{"pos":0,"teamName":"The Angry Polar Bears","goals":244,"passes":448,"goaliesWins":47,"goaliesShutOuts":2,"points":743,"goalsDiff":5,"passesDiff":45,"goaliesWinDiff":10,"goaliesShutOutsDiff":0,"pointsDiff":60,"userLogo":"etienne.png","bigLogo":"etienne.png","smallLogo":"etienne.png","teamUserName":"Etienne","playForCash":false,"hasPaid":false,"diffPosition":0},"worstLast14Days":{"pos":0,"teamName":"The Angry Polar Bears","goals":244,"passes":448,"goaliesWins":47,"goaliesShutOuts":2,"points":743,"goalsDiff":-36,"passesDiff":-35,"goaliesWinDiff":3,"goaliesShutOutsDiff":0,"pointsDiff":-68,"userLogo":"etienne.png","bigLogo":"etienne.png","smallLogo":"etienne.png","teamUserName":"Etienne","playForCash":false,"hasPaid":false,"diffPosition":0},"worstYesterday":{"pos":0,"teamName":"La Goth d\u0027Ottawa","goals":310,"passes":478,"goaliesWins":47,"goaliesShutOuts":2,"points":839,"goalsDiff":0,"passesDiff":1,"goaliesWinDiff":0,"goaliesShutOutsDiff":0,"pointsDiff":1,"userLogo":"eve.png","bigLogo":"eve.png","smallLogo":"eve.png","teamUserName":"Eve","playForCash":false,"hasPaid":false,"diffPosition":0}}