{"topTotalScore":1005,"lowTotalScore":824,"topScoreYesterday":11,"lowScoreYesterday":4,"leaders":[{"pos":1,"teamName":"gedagedigedagedao","goals":334,"passes":574,"goaliesWins":75,"goaliesShutOuts":11,"points":1005,"goalsDiff":6,"passesDiff":4,"goaliesWinDiff":1,"goaliesShutOutsDiff":0,"pointsDiff":11,"userLogo":"julien.png","bigLogo":"julien.png","smallLogo":"julien.png","teamUserName":"julien","playForCash":true,"hasPaid":false,"diffPosition":1},{"pos":2,"teamName":"Les huards","goals":350,"passes":581,"goaliesWins":61,"goaliesShutOuts":5,"points":1002,"goalsDiff":3,"passesDiff":3,"goaliesWinDiff":0,"goaliesShutOutsDiff":0,"pointsDiff":6,"userLogo":"louise.png","bigLogo":"louise.png","smallLogo":"louise.png","teamUserName":"Louise","playForCash":true,"hasPaid":false,"diffPosition":-1},{"pos":3,"teamName":"Laser Kiwi","goals":313,"passes":571,"goaliesWins":73,"goaliesShutOuts":12,"points":981,"goalsDiff":3,"passesDiff":2,"goaliesWinDiff":1,"goaliesShutOutsDiff":0,"pointsDiff":6,"userLogo":"guillaume.png","bigLogo":"guillaume.png","smallLogo":"guillaume.png","teamUserName":"Guillaume","playForCash":true,"hasPaid":false,"diffPosition":0},{"pos":4,"teamName":"Les Ducks","goals":353,"passes":558,"goaliesWins":48,"goaliesShutOuts":9,"points":977,"goalsDiff":7,"passesDiff":3,"goaliesWinDiff":0,"goaliesShutOutsDiff":0,"pointsDiff":10,"userLogo":"michel.png","bigLogo":"michel.png","smallLogo":"michel.png","teamUserName":"Michel","playForCash":true,"hasPaid":false,"diffPosition":0},{"pos":5,"teamName":"Les racails","goals":313,"passes":575,"goaliesWins":62,"goaliesShutOuts":8,"points":966,"goalsDiff":5,"passesDiff":5,"goaliesWinDiff":1,"goaliesShutOutsDiff":0,"pointsDiff":11,"userLogo":"jackson.png","bigLogo":"jackson.png","smallLogo":"jackson.png","teamUserName":"Jackson","playForCash":true,"hasPaid":false,"diffPosition":1},{"pos":5,"teamName":"Boston Trouble","goals":349,"passes":546,"goaliesWins":53,"goaliesShutOuts":9,"points":966,"goalsDiff":3,"passesDiff":1,"goaliesWinDiff":0,"goaliesShutOutsDiff":0,"pointsDiff":4,"userLogo":"hugo.png","bigLogo":"hugo.png","smallLogo":"hugo.png","teamUserName":"Hugo","playForCash":true,"hasPaid":false,"diffPosition":0},{"pos":6,"teamName":"les draconics","goals":314,"passes":555,"goaliesWins":62,"goaliesShutOuts":8,"points":947,"goalsDiff":3,"passesDiff":5,"goaliesWinDiff":1,"goaliesShutOutsDiff":0,"pointsDiff":9,"userLogo":"maddox.png","bigLogo":"maddox.png","smallLogo":"maddox.png","teamUserName":"maddox","playForCash":true,"hasPaid":false,"diffPosition":1},{"pos":7,"teamName":"SkiBum","goals":337,"passes":547,"goaliesWins":42,"goaliesShutOuts":7,"points":940,"goalsDiff":5,"passesDiff":6,"goaliesWinDiff":0,"goaliesShutOutsDiff":0,"pointsDiff":11,"userLogo":"jolyne.png","bigLogo":"jolyne.png","smallLogo":"jolyne.png","teamUserName":"Jolyne","playForCash":true,"hasPaid":false,"diffPosition":1},{"pos":8,"teamName":"Éperviers de Sorel-Tracy","goals":323,"passes":536,"goaliesWins":50,"goaliesShutOuts":10,"points":929,"goalsDiff":5,"passesDiff":3,"goaliesWinDiff":0,"goaliesShutOutsDiff":0,"pointsDiff":8,"userLogo":"alexandre.png","bigLogo":"alexandre.png","smallLogo":"alexandre.png","teamUserName":"Alexandre","playForCash":true,"hasPaid":false,"diffPosition":1},{"pos":9,"teamName":"Les voyageurs","goals":332,"passes":475,"goaliesWins":57,"goaliesShutOuts":7,"points":878,"goalsDiff":6,"passesDiff":5,"goaliesWinDiff":0,"goaliesShutOutsDiff":0,"pointsDiff":11,"userLogo":"etienne.png","bigLogo":"etienne.png","smallLogo":"etienne.png","teamUserName":"Étienne","playForCash":true,"hasPaid":false,"diffPosition":1},{"pos":10,"teamName":"Sherby","goals":298,"passes":449,"goaliesWins":61,"goaliesShutOuts":8,"points":824,"goalsDiff":1,"passesDiff":4,"goaliesWinDiff":0,"goaliesShutOutsDiff":0,"pointsDiff":5,"userLogo":"marjolaine.png","bigLogo":"marjolaine.png","smallLogo":"marjolaine.png","teamUserName":"Maarjolaine Comeau","playForCash":true,"hasPaid":false,"diffPosition":1}],"bestLast7Days":{"pos":0,"teamName":"Les racails","goals":313,"passes":575,"goaliesWins":62,"goaliesShutOuts":8,"points":966,"goalsDiff":25,"passesDiff":42,"goaliesWinDiff":3,"goaliesShutOutsDiff":0,"pointsDiff":70,"userLogo":"jackson.png","bigLogo":"jackson.png","smallLogo":"jackson.png","teamUserName":"Jackson","playForCash":false,"hasPaid":false,"diffPosition":0},"bestLast28Days":{"pos":0,"teamName":"Boston Trouble","goals":349,"passes":546,"goaliesWins":53,"goaliesShutOuts":9,"points":966,"goalsDiff":84,"passesDiff":129,"goaliesWinDiff":11,"goaliesShutOutsDiff":3,"pointsDiff":230,"userLogo":"hugo.png","bigLogo":"hugo.png","smallLogo":"hugo.png","teamUserName":"Hugo","playForCash":false,"hasPaid":false,"diffPosition":0},"bestLast14Days":{"pos":0,"teamName":"gedagedigedagedao","goals":334,"passes":574,"goaliesWins":75,"goaliesShutOuts":11,"points":1005,"goalsDiff":45,"passesDiff":61,"goaliesWinDiff":6,"goaliesShutOutsDiff":0,"pointsDiff":112,"userLogo":"julien.png","bigLogo":"julien.png","smallLogo":"julien.png","teamUserName":"julien","playForCash":false,"hasPaid":false,"diffPosition":0},"bestYesterday":{"pos":0,"teamName":"Les racails","goals":313,"passes":575,"goaliesWins":62,"goaliesShutOuts":8,"points":966,"goalsDiff":5,"passesDiff":5,"goaliesWinDiff":1,"goaliesShutOutsDiff":0,"pointsDiff":11,"userLogo":"jackson.png","bigLogo":"jackson.png","smallLogo":"jackson.png","teamUserName":"Jackson","playForCash":false,"hasPaid":false,"diffPosition":0},"bestTonight":{"pos":0,"goals":0,"passes":0,"goaliesWins":0,"goaliesShutOuts":0,"points":0,"goalsDiff":0,"passesDiff":0,"goaliesWinDiff":0,"goaliesShutOutsDiff":0,"pointsDiff":0,"playForCash":false,"hasPaid":false,"diffPosition":0},"worstLast7Days":{"pos":0,"teamName":"Laser Kiwi","goals":313,"passes":571,"goaliesWins":73,"goaliesShutOuts":12,"points":981,"goalsDiff":20,"passesDiff":20,"goaliesWinDiff":3,"goaliesShutOutsDiff":0,"pointsDiff":43,"userLogo":"guillaume.png","bigLogo":"guillaume.png","smallLogo":"guillaume.png","teamUserName":"Guillaume","playForCash":false,"hasPaid":false,"diffPosition":0},"worstLast28Days":{"pos":0,"teamName":"SkiBum","goals":337,"passes":547,"goaliesWins":42,"goaliesShutOuts":7,"points":940,"goalsDiff":74,"passesDiff":96,"goaliesWinDiff":4,"goaliesShutOutsDiff":0,"pointsDiff":174,"userLogo":"jolyne.png","bigLogo":"jolyne.png","smallLogo":"jolyne.png","teamUserName":"Jolyne","playForCash":false,"hasPaid":false,"diffPosition":0},"worstLast14Days":{"pos":0,"teamName":"SkiBum","goals":337,"passes":547,"goaliesWins":42,"goaliesShutOuts":7,"points":940,"goalsDiff":35,"passesDiff":43,"goaliesWinDiff":0,"goaliesShutOutsDiff":0,"pointsDiff":78,"userLogo":"jolyne.png","bigLogo":"jolyne.png","smallLogo":"jolyne.png","teamUserName":"Jolyne","playForCash":false,"hasPaid":false,"diffPosition":0},"worstYesterday":{"pos":0,"teamName":"Boston Trouble","goals":349,"passes":546,"goaliesWins":53,"goaliesShutOuts":9,"points":966,"goalsDiff":3,"passesDiff":1,"goaliesWinDiff":0,"goaliesShutOutsDiff":0,"pointsDiff":4,"userLogo":"hugo.png","bigLogo":"hugo.png","smallLogo":"hugo.png","teamUserName":"Hugo","playForCash":false,"hasPaid":false,"diffPosition":0}}