{"liveGames":[{"homeLogo":"http://a.espncdn.com/combiner/i?img\u003d/i/teamlogos/nhl/500/phi.png\u0026w\u003d25\u0026h\u003d25\u0026transparent\u003dtrue","awayLogo":"http://a.espncdn.com/combiner/i?img\u003d/i/teamlogos/nhl/500/cbj.png\u0026w\u003d25\u0026h\u003d25\u0026transparent\u003dtrue","homeScore":"1","awayScore":"1","period":"3rd","time":"0:25","gameUrl":"http://www.espn.com/nhl/boxscore?gameId\u003d400962493"},{"homeLogo":"http://a.espncdn.com/combiner/i?img\u003d/i/teamlogos/nhl/500/col.png\u0026w\u003d25\u0026h\u003d25\u0026transparent\u003dtrue","awayLogo":"http://a.espncdn.com/combiner/i?img\u003d/i/teamlogos/nhl/500/wpg.png\u0026w\u003d25\u0026h\u003d25\u0026transparent\u003dtrue","homeScore":"0","awayScore":"2","period":"2nd","time":"4:51","gameUrl":"http://www.espn.com/nhl/boxscore?gameId\u003d400962495"},{"homeLogo":"http://a.espncdn.com/combiner/i?img\u003d/i/teamlogos/nhl/500/nyi.png\u0026w\u003d25\u0026h\u003d25\u0026transparent\u003dtrue","awayLogo":"http://a.espncdn.com/combiner/i?img\u003d/i/teamlogos/nhl/500/car.png\u0026w\u003d25\u0026h\u003d25\u0026transparent\u003dtrue","homeScore":"1","awayScore":"1","period":"3rd","time":"16:03","gameUrl":"http://www.espn.com/nhl/boxscore?gameId\u003d400962494"},{"homeLogo":"http://a.espncdn.com/combiner/i?img\u003d/i/teamlogos/nhl/500/stl.png\u0026w\u003d25\u0026h\u003d25\u0026transparent\u003dtrue","awayLogo":"http://a.espncdn.com/combiner/i?img\u003d/i/teamlogos/nhl/500/dal.png\u0026w\u003d25\u0026h\u003d25\u0026transparent\u003dtrue","homeScore":"0","awayScore":"0","period":"1st, End","time":"","gameUrl":"http://www.espn.com/nhl/boxscore?gameId\u003d400962496"}],"newsUpdate":"Jeff Skinner  +1G"}